{
  "shed_id": 38,
  "shed_name": "S K.CHANDRALAL JAYAKUMARA",
  "shed_type": 1,
  "time_last_updated_by_shed": "2022-06-16 11:42",
  "time_last_updated_by_shed_ut": 1655359920,
  "fuel_type": "p92",
  "fuel_capacity": 335.0,
  "bowser_distatch": false,
  "eta": "",
  "did_shed_owner_update_today": false,
  "shed_code": "100049",
  "address": "Tiruwanaketiya - Agalawatte Rd, Nivithigala",
  "lat_lng": [
    6.596146,
    80.458298
  ],
  "time_last_updated_ut": 1655359920,
  "time_last_updated": "2022-06-16 11:42",
  "browser_dispatch": true,
  "dispatch_schedule_list": [
    {
      "time_dispatch_ut": 1655376360,
      "time_dispatch": "2022-06-16 16:16",
      "fuel_type": "d",
      "plant_name": "Kollonnawa",
      "amount": 6600.0,
      "time_last_updated_ut": 1655376900,
      "time_last_updated": "2022-06-16 16:25",
      "time_eta_ut": 1655387940,
      "time_eta": "2022-06-16 19:29"
    },
    {
      "time_dispatch_ut": 1655376360,
      "time_dispatch": "2022-06-16 16:16",
      "fuel_type": "p92",
      "plant_name": "Kollonnawa",
      "amount": 6600.0,
      "time_last_updated_ut": 1655376900,
      "time_last_updated": "2022-06-16 16:25",
      "time_eta_ut": 1655387940,
      "time_eta": "2022-06-16 19:29"
    }
  ],
  "fuel_status_idx": {
    "p92": {
      "is_available": true,
      "capacity": 335.0
    },
    "p95": {
      "is_available": true,
      "capacity": 0.0
    },
    "d": {
      "is_available": true,
      "capacity": 96.0
    },
    "sd": {
      "is_available": true,
      "capacity": 0.0
    },
    "k": {
      "is_available": true,
      "capacity": 450.0
    },
    "ik": {
      "is_available": true,
      "capacity": 0.0
    }
  }
}