{
  "shed_id": 1100,
  "shed_name": "R W H M U S B RAJAGURU",
  "shed_type": 1,
  "time_last_updated_by_shed": "2022-06-15 08:19",
  "time_last_updated_by_shed_ut": 1655261340,
  "fuel_type": "p92",
  "fuel_capacity": 500.0,
  "bowser_distatch": true,
  "eta": "2022-06-15 19:14, 6600L",
  "did_shed_owner_update_today": true,
  "shed_code": "104986",
  "address": "Madawala Road, Digana",
  "lat_lng": [
    7.309634,
    80.712379
  ],
  "time_last_updated_ut": 1655261340,
  "time_last_updated": "2022-06-15 08:19",
  "browser_dispatch": true,
  "dispatch_schedule_list": [
    {
      "time_dispatch_ut": 1655296800,
      "time_dispatch": "2022-06-15 18:10",
      "fuel_type": "p92",
      "plant_name": "Peradeniya",
      "amount": 6600.0,
      "time_last_updated_ut": 1655297400,
      "time_last_updated": "2022-06-15 18:20",
      "time_eta_ut": 1655300640,
      "time_eta": "2022-06-15 19:14"
    },
    {
      "time_dispatch_ut": 1655115300,
      "time_dispatch": "2022-06-13 15:45",
      "fuel_type": "d",
      "plant_name": "Peradeniya",
      "amount": 6600.0,
      "time_last_updated_ut": 1655115900,
      "time_last_updated": "2022-06-13 15:55",
      "time_eta_ut": 1655119140,
      "time_eta": "2022-06-13 16:49"
    },
    {
      "time_dispatch_ut": 1654943760,
      "time_dispatch": "2022-06-11 16:06",
      "fuel_type": "p95",
      "plant_name": "Kollonnawa",
      "amount": 6600.0,
      "time_last_updated_ut": 1654944300,
      "time_last_updated": "2022-06-11 16:15",
      "time_eta_ut": 1654959960,
      "time_eta": "2022-06-11 20:36"
    }
  ],
  "fuel_status_idx": {
    "p92": {
      "is_available": true,
      "capacity": 500.0
    },
    "p95": {
      "is_available": true,
      "capacity": 250.0
    },
    "d": {
      "is_available": true,
      "capacity": 672.0
    },
    "sd": {
      "is_available": true,
      "capacity": 250.0
    },
    "k": {
      "is_available": true,
      "capacity": 0.0
    },
    "ik": {
      "is_available": true,
      "capacity": 0.0
    }
  }
}