{
  "shed_id": 140,
  "shed_name": "L.L.KULATUNGA",
  "shed_type": 1,
  "time_last_updated_by_shed": "2022-06-16 07:12",
  "time_last_updated_by_shed_ut": 1655343720,
  "fuel_type": "p92",
  "fuel_capacity": 368.0,
  "bowser_distatch": false,
  "eta": "",
  "did_shed_owner_update_today": true,
  "shed_code": "100171",
  "address": "Colombo - Galle Main Rd, Kalutara",
  "lat_lng": [
    6.593237,
    79.95903
  ],
  "time_last_updated_ut": 1655343720,
  "time_last_updated": "2022-06-16 07:12",
  "browser_dispatch": true,
  "dispatch_schedule_list": [
    {
      "time_dispatch_ut": 1655114700,
      "time_dispatch": "2022-06-13 15:35",
      "fuel_type": "d",
      "plant_name": "Kollonnawa",
      "amount": 6600.0,
      "time_last_updated_ut": 1655115300,
      "time_last_updated": "2022-06-13 15:45",
      "time_eta_ut": 1655120640,
      "time_eta": "2022-06-13 17:14"
    },
    {
      "time_dispatch_ut": 1654920720,
      "time_dispatch": "2022-06-11 09:42",
      "fuel_type": "p92",
      "plant_name": "Kollonnawa",
      "amount": 6600.0,
      "time_last_updated_ut": 1654921200,
      "time_last_updated": "2022-06-11 09:50",
      "time_eta_ut": 1654926660,
      "time_eta": "2022-06-11 11:21"
    }
  ],
  "fuel_status_idx": {
    "p92": {
      "is_available": true,
      "capacity": 368.0
    },
    "p95": {
      "is_available": true,
      "capacity": 252.0
    },
    "d": {
      "is_available": true,
      "capacity": 524.0
    },
    "sd": {
      "is_available": true,
      "capacity": 0.0
    },
    "k": {
      "is_available": true,
      "capacity": 0.0
    },
    "ik": {
      "is_available": true,
      "capacity": 0.0
    }
  },
  "gmaps_address": "491 Colombo - Galle Main Rd, Wadduwa, Sri Lanka"
}