[
  {
    "shed_id": 784,
    "shed_name": "H.N.W.Priyangani De Silva, BERUWALA",
    "time_last_updated_by_shed": null,
    "time_last_updated_by_shed_ut": null,
    "fuel_type": "p92",
    "fuel_capacity": 0.0,
    "bowser_distatch": true,
    "eta": "2022-06-15 22:14, 6600L",
    "did_shed_owner_update_today": false
  },
  {
    "shed_id": 287,
    "shed_name": "S.A.SIRIPALA TEL PIRAWUMHALA, PELAWATTE",
    "time_last_updated_by_shed": "2022-06-15 09:19",
    "time_last_updated_by_shed_ut": 1655264940,
    "fuel_type": "p92",
    "fuel_capacity": 0.0,
    "bowser_distatch": true,
    "eta": "2022-06-15 21:47, 6600L",
    "did_shed_owner_update_today": true
  },
  {
    "shed_id": 749,
    "shed_name": "S P GUNASINGHE, MATUGAMA",
    "time_last_updated_by_shed": null,
    "time_last_updated_by_shed_ut": null,
    "fuel_type": "p92",
    "fuel_capacity": 0.0,
    "bowser_distatch": true,
    "eta": "2022-06-15 21:13, 6600L",
    "did_shed_owner_update_today": false
  },
  {
    "shed_id": 671,
    "shed_name": "CANCEL-AGALAWATTA MPCS LTD, ITTAPANA",
    "time_last_updated_by_shed": "2022-06-15 09:11",
    "time_last_updated_by_shed_ut": 1655264460,
    "fuel_type": "p92",
    "fuel_capacity": 366.0,
    "bowser_distatch": true,
    "eta": "2022-06-15 20:48, 6600L",
    "did_shed_owner_update_today": true
  },
  {
    "shed_id": 1195,
    "shed_name": "LITRO GAS LANKA (PVT) LTD, WELIPENNE - SITE B",
    "time_last_updated_by_shed": "2022-06-15 07:07",
    "time_last_updated_by_shed_ut": 1655257020,
    "fuel_type": "p92",
    "fuel_capacity": 219.0,
    "bowser_distatch": true,
    "eta": "2022-06-15 20:44, 6600L",
    "did_shed_owner_update_today": true
  },
  {
    "shed_id": 524,
    "shed_name": "AGALAWATTA MPCS LTD, BADURELIYA",
    "time_last_updated_by_shed": "2022-06-15 09:28",
    "time_last_updated_by_shed_ut": 1655265480,
    "fuel_type": "p92",
    "fuel_capacity": 116.0,
    "bowser_distatch": true,
    "eta": "2022-06-15 19:44, 6600L",
    "did_shed_owner_update_today": true
  },
  {
    "shed_id": 915,
    "shed_name": "S.P.LANKA PETROLEUM (PVT) LTD, AGALAWATTA",
    "time_last_updated_by_shed": "2022-06-15 09:01",
    "time_last_updated_by_shed_ut": 1655263860,
    "fuel_type": "p92",
    "fuel_capacity": 327.0,
    "bowser_distatch": true,
    "eta": "2022-06-15 19:23, 6600L",
    "did_shed_owner_update_today": true
  },
  {
    "shed_id": 1137,
    "shed_name": "J A D R JAYALATH, DODANGODA",
    "time_last_updated_by_shed": "2022-06-15 10:28",
    "time_last_updated_by_shed_ut": 1655269080,
    "fuel_type": "p92",
    "fuel_capacity": 481.0,
    "bowser_distatch": true,
    "eta": "2022-06-15 18:44, 6600L",
    "did_shed_owner_update_today": true
  },
  {
    "shed_id": 1232,
    "shed_name": "M D S NISHANTHI, ANGURUWATHOTA",
    "time_last_updated_by_shed": "2022-06-14 10:44",
    "time_last_updated_by_shed_ut": 1655183640,
    "fuel_type": "p92",
    "fuel_capacity": 89.0,
    "bowser_distatch": true,
    "eta": "2022-06-15 16:51, 6600L",
    "did_shed_owner_update_today": false
  },
  {
    "shed_id": 950,
    "shed_name": "M W J KARUNARATHNE, BELLAPITIYA,ANGURUWATHOTA",
    "time_last_updated_by_shed": "2022-06-15 07:39",
    "time_last_updated_by_shed_ut": 1655258940,
    "fuel_type": "p92",
    "fuel_capacity": 912.0,
    "bowser_distatch": true,
    "eta": "2022-06-15 16:42, 6600L",
    "did_shed_owner_update_today": true
  },
  {
    "shed_id": 11,
    "shed_name": "MRS. S.L.HETTIARACHCHI & SONS, HORANA",
    "time_last_updated_by_shed": "2022-06-14 09:25",
    "time_last_updated_by_shed_ut": 1655178900,
    "fuel_type": "p92",
    "fuel_capacity": 696.0,
    "bowser_distatch": true,
    "eta": "2022-06-15 16:38, 6600L",
    "did_shed_owner_update_today": false
  },
  {
    "shed_id": 438,
    "shed_name": "BULATHSINHALA MPCS LTD, BULATHSINHALA",
    "time_last_updated_by_shed": "2022-06-15 09:58",
    "time_last_updated_by_shed_ut": 1655267280,
    "fuel_type": "p92",
    "fuel_capacity": 923.0,
    "bowser_distatch": true,
    "eta": "2022-06-15 15:31, 6600L",
    "did_shed_owner_update_today": true
  },
  {
    "shed_id": 847,
    "shed_name": "GANGE KULARATNE, BULATHSINHALA",
    "time_last_updated_by_shed": "2022-06-15 09:53",
    "time_last_updated_by_shed_ut": 1655266980,
    "fuel_type": "p92",
    "fuel_capacity": 854.0,
    "bowser_distatch": true,
    "eta": "2022-06-15 15:31, 6600L",
    "did_shed_owner_update_today": true
  },
  {
    "shed_id": 1218,
    "shed_name": "P A K D JEEWANTHI, MOLLIGODA",
    "time_last_updated_by_shed": "2022-06-15 09:12",
    "time_last_updated_by_shed_ut": 1655264520,
    "fuel_type": "p92",
    "fuel_capacity": 540.0,
    "bowser_distatch": true,
    "eta": "2022-06-15 12:55, 6600L",
    "did_shed_owner_update_today": true
  },
  {
    "shed_id": 454,
    "shed_name": "AUTO CARE CENTRE (PVT) LTD, PANADURA",
    "time_last_updated_by_shed": "2022-06-15 08:48",
    "time_last_updated_by_shed_ut": 1655263080,
    "fuel_type": "p92",
    "fuel_capacity": 244.0,
    "bowser_distatch": true,
    "eta": "2022-06-15 12:34, 6600L",
    "did_shed_owner_update_today": true
  },
  {
    "shed_id": 90,
    "shed_name": "BERUWALA MPCS LTD, MAGGONA",
    "time_last_updated_by_shed": "2022-06-15 07:08",
    "time_last_updated_by_shed_ut": 1655257080,
    "fuel_type": "p92",
    "fuel_capacity": 1020.0,
    "bowser_distatch": true,
    "eta": "2022-06-15 12:08, 6600L",
    "did_shed_owner_update_today": true
  },
  {
    "shed_id": 126,
    "shed_name": "ANOJA FERNANDO, KATUKURUNDA",
    "time_last_updated_by_shed": "2022-06-15 07:23",
    "time_last_updated_by_shed_ut": 1655257980,
    "fuel_type": "p92",
    "fuel_capacity": 85.0,
    "bowser_distatch": true,
    "eta": "2022-06-15 11:51, 6600L",
    "did_shed_owner_update_today": true
  },
  {
    "shed_id": 48,
    "shed_name": "SAGANA ENTERPRISES (PVT) LTD, KALUTARA NORTH",
    "time_last_updated_by_shed": "2022-06-15 10:15",
    "time_last_updated_by_shed_ut": 1655268300,
    "fuel_type": "p92",
    "fuel_capacity": 88.0,
    "bowser_distatch": true,
    "eta": "2022-06-15 11:42, 6600L",
    "did_shed_owner_update_today": true
  },
  {
    "shed_id": 963,
    "shed_name": "P W RODRIGO, PANAPITIYA ,KALUTHARA",
    "time_last_updated_by_shed": "2022-06-15 08:28",
    "time_last_updated_by_shed_ut": 1655261880,
    "fuel_type": "p92",
    "fuel_capacity": 518.0,
    "bowser_distatch": true,
    "eta": "2022-06-15 11:42, 6600L",
    "did_shed_owner_update_today": true
  },
  {
    "shed_id": 1313,
    "shed_name": "D I G D P GUNASEKARA, KUMBUKA WEST",
    "time_last_updated_by_shed": "2022-06-15 16:21",
    "time_last_updated_by_shed_ut": 1655290260,
    "fuel_type": "p92",
    "fuel_capacity": 580.0,
    "bowser_distatch": false,
    "eta": "",
    "did_shed_owner_update_today": true
  },
  {
    "shed_id": 866,
    "shed_name": "MALALATHUNGA CONSTRUCTION (PVT)LTD, NEBODA",
    "time_last_updated_by_shed": "2022-06-15 14:56",
    "time_last_updated_by_shed_ut": 1655285160,
    "fuel_type": "p92",
    "fuel_capacity": 880.0,
    "bowser_distatch": false,
    "eta": "",
    "did_shed_owner_update_today": true
  },
  {
    "shed_id": 1332,
    "shed_name": "G K C K PRASANNA, INGIRIYA",
    "time_last_updated_by_shed": "2022-06-15 14:35",
    "time_last_updated_by_shed_ut": 1655283900,
    "fuel_type": "p92",
    "fuel_capacity": 2200.0,
    "bowser_distatch": false,
    "eta": "",
    "did_shed_owner_update_today": true
  },
  {
    "shed_id": 832,
    "shed_name": "H SRIYANI PATRICIA FONSEKA, PAYAGALA",
    "time_last_updated_by_shed": "2022-06-15 13:37",
    "time_last_updated_by_shed_ut": 1655280420,
    "fuel_type": "p92",
    "fuel_capacity": 0.0,
    "bowser_distatch": false,
    "eta": "",
    "did_shed_owner_update_today": true
  },
  {
    "shed_id": 323,
    "shed_name": "S.K.RAJAPAKSE, PANADURA",
    "time_last_updated_by_shed": "2022-06-15 12:49",
    "time_last_updated_by_shed_ut": 1655277540,
    "fuel_type": "p92",
    "fuel_capacity": 12.0,
    "bowser_distatch": false,
    "eta": "",
    "did_shed_owner_update_today": true
  },
  {
    "shed_id": 160,
    "shed_name": "SAPTARA ENTERPRISES, BERUWALA",
    "time_last_updated_by_shed": "2022-06-15 12:07",
    "time_last_updated_by_shed_ut": 1655275020,
    "fuel_type": "p92",
    "fuel_capacity": 285.0,
    "bowser_distatch": false,
    "eta": "",
    "did_shed_owner_update_today": true
  },
  {
    "shed_id": 133,
    "shed_name": "H D C HOLDINGS ( PVT ) LTD, HORANA",
    "time_last_updated_by_shed": "2022-06-15 10:37",
    "time_last_updated_by_shed_ut": 1655269620,
    "fuel_type": "p92",
    "fuel_capacity": 30.0,
    "bowser_distatch": false,
    "eta": "",
    "did_shed_owner_update_today": true
  },
  {
    "shed_id": 954,
    "shed_name": "FISHERIES DEPARTMENT, BERUWALA",
    "time_last_updated_by_shed": "2022-06-15 10:32",
    "time_last_updated_by_shed_ut": 1655269320,
    "fuel_type": "p92",
    "fuel_capacity": 0.0,
    "bowser_distatch": false,
    "eta": "",
    "did_shed_owner_update_today": true
  },
  {
    "shed_id": 88,
    "shed_name": "D.W.A .HAPUARACHCHI & COMPANY, BANDARAGAMA",
    "time_last_updated_by_shed": "2022-06-15 09:58",
    "time_last_updated_by_shed_ut": 1655267280,
    "fuel_type": "p92",
    "fuel_capacity": 992.0,
    "bowser_distatch": false,
    "eta": "",
    "did_shed_owner_update_today": true
  },
  {
    "shed_id": 571,
    "shed_name": "CEYLON FISHERIES HARBOUR CORPORATIO, BERUWALA",
    "time_last_updated_by_shed": "2022-06-15 09:55",
    "time_last_updated_by_shed_ut": 1655267100,
    "fuel_type": "p92",
    "fuel_capacity": 0.0,
    "bowser_distatch": false,
    "eta": "",
    "did_shed_owner_update_today": true
  },
  {
    "shed_id": 935,
    "shed_name": "S L WASANTHA, MORAGAHAHENA",
    "time_last_updated_by_shed": "2022-06-15 09:36",
    "time_last_updated_by_shed_ut": 1655265960,
    "fuel_type": "p92",
    "fuel_capacity": 750.0,
    "bowser_distatch": false,
    "eta": "",
    "did_shed_owner_update_today": true
  },
  {
    "shed_id": 1319,
    "shed_name": "LANKA FILLING STATION YATADOLA, YATADOLA, MATHUGAMA",
    "time_last_updated_by_shed": "2022-06-15 09:24",
    "time_last_updated_by_shed_ut": 1655265240,
    "fuel_type": "p92",
    "fuel_capacity": 125.0,
    "bowser_distatch": false,
    "eta": "",
    "did_shed_owner_update_today": true
  },
  {
    "shed_id": 64,
    "shed_name": "H.D.PEIRIS & COMPANY, PANADURA",
    "time_last_updated_by_shed": "2022-06-15 09:16",
    "time_last_updated_by_shed_ut": 1655264760,
    "fuel_type": "p92",
    "fuel_capacity": 408.0,
    "bowser_distatch": false,
    "eta": "",
    "did_shed_owner_update_today": true
  },
  {
    "shed_id": 605,
    "shed_name": " L. I.JAYANTHA DE SILVA, BERUWALA",
    "time_last_updated_by_shed": "2022-06-15 09:09",
    "time_last_updated_by_shed_ut": 1655264340,
    "fuel_type": "p92",
    "fuel_capacity": 0.0,
    "bowser_distatch": false,
    "eta": "",
    "did_shed_owner_update_today": true
  },
  {
    "shed_id": 193,
    "shed_name": "P K CHITHRA DAMAYANTHI, ARAKAWILA - HANDAPANGODA",
    "time_last_updated_by_shed": "2022-06-15 08:59",
    "time_last_updated_by_shed_ut": 1655263740,
    "fuel_type": "p92",
    "fuel_capacity": 435.0,
    "bowser_distatch": false,
    "eta": "",
    "did_shed_owner_update_today": true
  },
  {
    "shed_id": 1268,
    "shed_name": "DAMITH ENTERPRISES, POKUNUWITA",
    "time_last_updated_by_shed": "2022-06-15 08:38",
    "time_last_updated_by_shed_ut": 1655262480,
    "fuel_type": "p92",
    "fuel_capacity": 324.0,
    "bowser_distatch": false,
    "eta": "",
    "did_shed_owner_update_today": true
  },
  {
    "shed_id": 360,
    "shed_name": "BANDARAGAMA MPCS LTD, BANDARAGAMA",
    "time_last_updated_by_shed": "2022-06-15 08:35",
    "time_last_updated_by_shed_ut": 1655262300,
    "fuel_type": "p92",
    "fuel_capacity": 250.0,
    "bowser_distatch": false,
    "eta": "",
    "did_shed_owner_update_today": true
  },
  {
    "shed_id": 1287,
    "shed_name": "JAYALATH ENTERPRISES, WELIPENNA",
    "time_last_updated_by_shed": "2022-06-15 08:16",
    "time_last_updated_by_shed_ut": 1655261160,
    "fuel_type": "p92",
    "fuel_capacity": 1003.0,
    "bowser_distatch": false,
    "eta": "",
    "did_shed_owner_update_today": true
  },
  {
    "shed_id": 1238,
    "shed_name": "P M WIMALASIRI, PAYAGALA",
    "time_last_updated_by_shed": "2022-06-15 08:14",
    "time_last_updated_by_shed_ut": 1655261040,
    "fuel_type": "p92",
    "fuel_capacity": 110.0,
    "bowser_distatch": false,
    "eta": "",
    "did_shed_owner_update_today": true
  },
  {
    "shed_id": 3,
    "shed_name": "K.N.PERERA & SONS, PANADURA",
    "time_last_updated_by_shed": "2022-06-15 08:13",
    "time_last_updated_by_shed_ut": 1655260980,
    "fuel_type": "p92",
    "fuel_capacity": 698.0,
    "bowser_distatch": false,
    "eta": "",
    "did_shed_owner_update_today": true
  },
  {
    "shed_id": 846,
    "shed_name": "L W  SURAGE, HORANA",
    "time_last_updated_by_shed": "2022-06-15 08:12",
    "time_last_updated_by_shed_ut": 1655260920,
    "fuel_type": "p92",
    "fuel_capacity": 530.0,
    "bowser_distatch": false,
    "eta": "",
    "did_shed_owner_update_today": true
  },
  {
    "shed_id": 1298,
    "shed_name": "H D BUDDHIPALA INDANA PIRAUMHALA, INGIRIYA",
    "time_last_updated_by_shed": "2022-06-15 08:00",
    "time_last_updated_by_shed_ut": 1655260200,
    "fuel_type": "p92",
    "fuel_capacity": 490.0,
    "bowser_distatch": false,
    "eta": "",
    "did_shed_owner_update_today": true
  },
  {
    "shed_id": 618,
    "shed_name": "M.G.M.IMTIYAZ, BERUELA -GORAKADOOWA",
    "time_last_updated_by_shed": "2022-06-15 07:51",
    "time_last_updated_by_shed_ut": 1655259660,
    "fuel_type": "p92",
    "fuel_capacity": 0.0,
    "bowser_distatch": false,
    "eta": "",
    "did_shed_owner_update_today": true
  },
  {
    "shed_id": 1230,
    "shed_name": "S SEPALA, BATAGODA",
    "time_last_updated_by_shed": "2022-06-15 07:47",
    "time_last_updated_by_shed_ut": 1655259420,
    "fuel_type": "p92",
    "fuel_capacity": 734.0,
    "bowser_distatch": false,
    "eta": "",
    "did_shed_owner_update_today": true
  },
  {
    "shed_id": 262,
    "shed_name": "PANADURA MPCS LTD, WADDUWA",
    "time_last_updated_by_shed": "2022-06-15 07:36",
    "time_last_updated_by_shed_ut": 1655258760,
    "fuel_type": "p92",
    "fuel_capacity": 179.0,
    "bowser_distatch": false,
    "eta": "",
    "did_shed_owner_update_today": true
  },
  {
    "shed_id": 89,
    "shed_name": "BERUWALA MPCS LTD, ALUTHGAMA",
    "time_last_updated_by_shed": "2022-06-15 07:34",
    "time_last_updated_by_shed_ut": 1655258640,
    "fuel_type": "p92",
    "fuel_capacity": 249.0,
    "bowser_distatch": false,
    "eta": "",
    "did_shed_owner_update_today": true
  },
  {
    "shed_id": 111,
    "shed_name": "R.N.D.ALWIS SENEVIRATNE, KALUTARA SOUTH",
    "time_last_updated_by_shed": "2022-06-15 07:18",
    "time_last_updated_by_shed_ut": 1655257680,
    "fuel_type": "p92",
    "fuel_capacity": 200.0,
    "bowser_distatch": false,
    "eta": "",
    "did_shed_owner_update_today": true
  },
  {
    "shed_id": 140,
    "shed_name": "L.L.KULATUNGA, KALUTARA NORTH",
    "time_last_updated_by_shed": "2022-06-15 07:09",
    "time_last_updated_by_shed_ut": 1655257140,
    "fuel_type": "p92",
    "fuel_capacity": 368.0,
    "bowser_distatch": false,
    "eta": "",
    "did_shed_owner_update_today": true
  },
  {
    "shed_id": 445,
    "shed_name": "PANADURA AUTO SERVICE & FILLING STN, PANADURA",
    "time_last_updated_by_shed": "2022-06-15 05:53",
    "time_last_updated_by_shed_ut": 1655252580,
    "fuel_type": "p92",
    "fuel_capacity": 249.0,
    "bowser_distatch": false,
    "eta": "",
    "did_shed_owner_update_today": true
  },
  {
    "shed_id": 951,
    "shed_name": "P.PRADEEP MIHINATH FERNANDO, PANADURA",
    "time_last_updated_by_shed": "2022-06-15 05:52",
    "time_last_updated_by_shed_ut": 1655252520,
    "fuel_type": "p92",
    "fuel_capacity": 249.0,
    "bowser_distatch": false,
    "eta": "",
    "did_shed_owner_update_today": true
  },
  {
    "shed_id": 104,
    "shed_name": "MS. RELIANCE CHEMICALS COMPANY (PVT, MORONTUDUWA",
    "time_last_updated_by_shed": "2022-06-15 04:16",
    "time_last_updated_by_shed_ut": 1655246760,
    "fuel_type": "p92",
    "fuel_capacity": 260.0,
    "bowser_distatch": false,
    "eta": "",
    "did_shed_owner_update_today": true
  },
  {
    "shed_id": 442,
    "shed_name": "A.M. ENTERPRISES, BERUWALA",
    "time_last_updated_by_shed": "2022-06-14 08:16",
    "time_last_updated_by_shed_ut": 1655174760,
    "fuel_type": "p92",
    "fuel_capacity": 89.0,
    "bowser_distatch": false,
    "eta": "",
    "did_shed_owner_update_today": false
  },
  {
    "shed_id": 896,
    "shed_name": "M.H.S.D.PIYASENA, POLEGODA- MAHAGAMA",
    "time_last_updated_by_shed": "2022-06-14 07:51",
    "time_last_updated_by_shed_ut": 1655173260,
    "fuel_type": "p92",
    "fuel_capacity": 52.0,
    "bowser_distatch": false,
    "eta": "",
    "did_shed_owner_update_today": false
  },
  {
    "shed_id": 298,
    "shed_name": "MATHUGAMA MPCS LTD, MATUGAMA",
    "time_last_updated_by_shed": "2022-06-13 07:59",
    "time_last_updated_by_shed_ut": 1655087340,
    "fuel_type": "p92",
    "fuel_capacity": 334.0,
    "bowser_distatch": false,
    "eta": "",
    "did_shed_owner_update_today": false
  },
  {
    "shed_id": 329,
    "shed_name": "MATUGAMA AGENCY (PVT) LTD, MATUGAMA",
    "time_last_updated_by_shed": "2022-06-12 21:45",
    "time_last_updated_by_shed_ut": 1655050500,
    "fuel_type": "p92",
    "fuel_capacity": 236.0,
    "bowser_distatch": false,
    "eta": "",
    "did_shed_owner_update_today": false
  },
  {
    "shed_id": 752,
    "shed_name": "S & D ENTERPRISES, PANADURA",
    "time_last_updated_by_shed": null,
    "time_last_updated_by_shed_ut": null,
    "fuel_type": "p92",
    "fuel_capacity": 0.0,
    "bowser_distatch": false,
    "eta": "",
    "did_shed_owner_update_today": false
  },
  {
    "shed_id": 738,
    "shed_name": "SAMARANAYAKA SAHA SAMARANAYAKA, AGALAWATTA",
    "time_last_updated_by_shed": null,
    "time_last_updated_by_shed_ut": null,
    "fuel_type": "p92",
    "fuel_capacity": 0.0,
    "bowser_distatch": false,
    "eta": "",
    "did_shed_owner_update_today": false
  },
  {
    "shed_id": 745,
    "shed_name": "B D P GUNASEKERA & SONS, HORANA",
    "time_last_updated_by_shed": null,
    "time_last_updated_by_shed_ut": null,
    "fuel_type": "p92",
    "fuel_capacity": 0.0,
    "bowser_distatch": false,
    "eta": "",
    "did_shed_owner_update_today": false
  },
  {
    "shed_id": 746,
    "shed_name": "RAIGAM UDAGAHAPATTU MPCS LTD, INGIRIYA",
    "time_last_updated_by_shed": null,
    "time_last_updated_by_shed_ut": null,
    "fuel_type": "p92",
    "fuel_capacity": 0.0,
    "bowser_distatch": false,
    "eta": "",
    "did_shed_owner_update_today": false
  },
  {
    "shed_id": 748,
    "shed_name": "KALUTARA MPCS LTD, KALUTARA SOUTH",
    "time_last_updated_by_shed": null,
    "time_last_updated_by_shed_ut": null,
    "fuel_type": "p92",
    "fuel_capacity": 0.0,
    "bowser_distatch": false,
    "eta": "",
    "did_shed_owner_update_today": false
  },
  {
    "shed_id": 976,
    "shed_name": "Raigam Udagahapattu MPCS LTD-B, PORUWADANDA",
    "time_last_updated_by_shed": null,
    "time_last_updated_by_shed_ut": null,
    "fuel_type": "p92",
    "fuel_capacity": 0.0,
    "bowser_distatch": false,
    "eta": "",
    "did_shed_owner_update_today": false
  },
  {
    "shed_id": 781,
    "shed_name": "D W FERNANDO AND SONS PVT. LTD., ALUTHGAMA",
    "time_last_updated_by_shed": null,
    "time_last_updated_by_shed_ut": null,
    "fuel_type": "p92",
    "fuel_capacity": 0.0,
    "bowser_distatch": false,
    "eta": "",
    "did_shed_owner_update_today": false
  },
  {
    "shed_id": 1160,
    "shed_name": "P.L.R..C.COORAY, BERUWALA",
    "time_last_updated_by_shed": null,
    "time_last_updated_by_shed_ut": null,
    "fuel_type": "p92",
    "fuel_capacity": 0.0,
    "bowser_distatch": false,
    "eta": "",
    "did_shed_owner_update_today": false
  },
  {
    "shed_id": 1082,
    "shed_name": "SOUTHERN PETROLEUM (PVT) LTD - 7, BANDARAGAMA",
    "time_last_updated_by_shed": null,
    "time_last_updated_by_shed_ut": null,
    "fuel_type": "p92",
    "fuel_capacity": 0.0,
    "bowser_distatch": false,
    "eta": "",
    "did_shed_owner_update_today": false
  },
  {
    "shed_id": 1067,
    "shed_name": "A J M FARRY. (M/s. A J FUEL MART), ALUTHGAMA",
    "time_last_updated_by_shed": null,
    "time_last_updated_by_shed_ut": null,
    "fuel_type": "p92",
    "fuel_capacity": 0.0,
    "bowser_distatch": false,
    "eta": "",
    "did_shed_owner_update_today": false
  },
  {
    "shed_id": 1033,
    "shed_name": "S LALITH PERERA, BANDARAGAMA",
    "time_last_updated_by_shed": null,
    "time_last_updated_by_shed_ut": null,
    "fuel_type": "p92",
    "fuel_capacity": 0.0,
    "bowser_distatch": false,
    "eta": "",
    "did_shed_owner_update_today": false
  }
]