{
  "shed_id": 532,
  "shed_name": "WARAKAPOLA MPCS LTD",
  "shed_type": 1,
  "time_last_updated_by_shed": "2022-06-17 09:17",
  "time_last_updated_by_shed_ut": 1655437620,
  "fuel_type": "p92",
  "fuel_capacity": 420.0,
  "bowser_distatch": false,
  "eta": null,
  "eta_ut": null,
  "eta_amount": null,
  "did_shed_owner_update_today": true,
  "shed_code": "100637",
  "address": "Kandy Road, Warakapola",
  "lat_lng": [
    7.230469,
    80.201935
  ],
  "time_last_updated_ut": 1655437620,
  "time_last_updated": "2022-06-17 09:17",
  "browser_dispatch": true,
  "dispatch_schedule_list": [
    {
      "time_dispatch_ut": 1655384040,
      "time_dispatch": "2022-06-16 18:24",
      "fuel_type": "d",
      "plant_name": "Kollonnawa",
      "amount": 6600.0,
      "time_last_updated_ut": 1655384700,
      "time_last_updated": "2022-06-16 18:35",
      "time_eta_ut": 1655391240,
      "time_eta": "2022-06-16 20:24"
    },
    {
      "time_dispatch_ut": 1655286000,
      "time_dispatch": "2022-06-15 15:10",
      "fuel_type": "p92",
      "plant_name": "Muthurajawela",
      "amount": 6600.0,
      "time_last_updated_ut": 1655286600,
      "time_last_updated": "2022-06-15 15:20",
      "time_eta_ut": 1655313780,
      "time_eta": "2022-06-15 22:53"
    }
  ],
  "fuel_status_idx": {
    "p92": {
      "is_available": true,
      "capacity": 420.0
    },
    "p95": {
      "is_available": true,
      "capacity": 0.0
    },
    "d": {
      "is_available": true,
      "capacity": 488.0
    },
    "sd": {
      "is_available": true,
      "capacity": 0.0
    },
    "k": {
      "is_available": true,
      "capacity": 268.0
    },
    "ik": {
      "is_available": true,
      "capacity": 0.0
    }
  }
}