{
  "shed_id": 52,
  "shed_name": "CHANDANA FILLING STATION",
  "shed_type": 1,
  "time_last_updated_by_shed": "2022-06-17 08:50",
  "time_last_updated_by_shed_ut": 1655436000,
  "fuel_type": "p92",
  "fuel_capacity": 387.0,
  "bowser_distatch": false,
  "eta": null,
  "eta_ut": null,
  "eta_amount": null,
  "did_shed_owner_update_today": true,
  "shed_code": "100063",
  "address": "No 237 60100, Kurunegala -Narammala - Madampe Rd, Narammala",
  "lat_lng": [
    7.436151,
    80.221748
  ],
  "time_last_updated_ut": 1655436000,
  "time_last_updated": "2022-06-17 08:50",
  "browser_dispatch": true,
  "dispatch_schedule_list": [
    {
      "time_dispatch_ut": 1655463900,
      "time_dispatch": "2022-06-17 16:35",
      "fuel_type": "p95",
      "plant_name": "Kollonnawa",
      "amount": 6600.0,
      "time_last_updated_ut": 1655464500,
      "time_last_updated": "2022-06-17 16:45",
      "time_eta_ut": 1655473440,
      "time_eta": "2022-06-17 19:14"
    },
    {
      "time_dispatch_ut": 1655363400,
      "time_dispatch": "2022-06-16 12:40",
      "fuel_type": "p92",
      "plant_name": "Muthurajawela",
      "amount": 6600.0,
      "time_last_updated_ut": 1655364000,
      "time_last_updated": "2022-06-16 12:50",
      "time_eta_ut": 1655372400,
      "time_eta": "2022-06-16 15:10"
    },
    {
      "time_dispatch_ut": 1655104920,
      "time_dispatch": "2022-06-13 12:52",
      "fuel_type": "d",
      "plant_name": "Sapugaskhanda",
      "amount": 13200.0,
      "time_last_updated_ut": 1655105400,
      "time_last_updated": "2022-06-13 13:00",
      "time_eta_ut": null,
      "time_eta": null
    }
  ],
  "fuel_status_idx": {
    "p92": {
      "is_available": true,
      "capacity": 387.0
    },
    "p95": {
      "is_available": true,
      "capacity": 325.0
    },
    "d": {
      "is_available": true,
      "capacity": 161.0
    },
    "sd": {
      "is_available": true,
      "capacity": 328.0
    },
    "k": {
      "is_available": true,
      "capacity": 77.0
    },
    "ik": {
      "is_available": true,
      "capacity": 0.0
    }
  }
}